{
  "events": {
    "1": {
      "id": 1,
      "title": "Tip Top Taste",
      "description": "Test",
      "start_date": null,
      "end_date": null,
      "venue_name": null,
      "street_address": null,
      "city": "Atlanta",
      "state": "GA",
      "zip_code": null,
      "category": null,
      "created_at": "2026-02-15T19:07:40.113765+00:00",
      "updated_at": "2026-02-16T02:14:06.148660+00:00",
      "published": false,
      "archived": false,
      "requirements_published": true,
      "layout_published": true
    },
    "2": {
      "id": 2,
      "title": "Tip Top Taste",
      "description": "Test",
      "start_date": null,
      "end_date": null,
      "venue_name": null,
      "street_address": null,
      "city": null,
      "state": null,
      "zip_code": null,
      "category": "Food",
      "created_at": "2026-02-15T19:19:10.564274+00:00",
      "updated_at": "2026-02-16T01:19:33.664123+00:00",
      "published": false,
      "archived": false,
      "requirements_published": false,
      "layout_published": false
    }
  },
  "requirements": {
    "1": {
      "version": 2,
      "requirements": {
        "document_requirements": [],
        "payment_settings": {
          "require_deposit": true,
          "refund_policy": "No Refunds",
          "payment_notes": "",
          "deposit_percent": 50,
          "late_fee": 0
        },
        "compliance_items": [
          {
            "id": "c1",
            "text": "Electrical equipment inspected and certified.",
            "required": true
          }
        ],
        "booth_categories": [],
        "custom_restrictions": [],
        "event_id": 1,
        "updated_at": "2026-02-16T02:13:53.179122+00:00"
      }
    },
    "2": {
      "version": 2,
      "requirements": {
        "event_id": 2,
        "booth_categories": [],
        "custom_restrictions": [],
        "compliance_items": [],
        "document_requirements": [],
        "payment_settings": {
          "require_deposit": true,
          "deposit_percent": 50,
          "late_fee": 0,
          "refund_policy": "No Refunds",
          "payment_notes": ""
        },
        "updated_at": "2026-02-16T01:19:28.027627+00:00"
      }
    }
  },
  "diagrams": {
    "2": {
      "diagram": {
        "elements": [],
        "meta": {}
      },
      "version": 0
    },
    "1": {
      "diagram": {
        "canvas": {
          "width": 1200,
          "height": 800,
          "gridSize": 20
        },
        "levels": [
          {
            "id": "level-1",
            "name": "Level 1",
            "booths": [
              {
                "id": "booth-14edbc7f44e27-1771092745064",
                "x": 140,
                "y": 140,
                "width": 120,
                "height": 80,
                "label": "Booth 1",
                "status": "available",
                "category": "Food & Beverage",
                "price": 500
              },
              {
                "id": "booth-b144a4f591f9-1771092748679",
                "x": 484.92753623188406,
                "y": 151.59420289855072,
                "width": 202.60869565217394,
                "height": 148.1159420289855,
                "label": "Booth 2",
                "status": "available",
                "category": "Food & Beverage",
                "price": 500
              },
              {
                "id": "booth-63db4cc24e75c8-1771104911658",
                "x": 190.72463768115944,
                "y": 440,
                "width": 120,
                "height": 80,
                "label": "Booth 3",
                "status": "available",
                "category": "Food & Beverage",
                "price": 500
              }
            ],
            "elements": []
          }
        ]
      },
      "version": 1,
      "updated_at": "2026-02-15T21:00:39.547038+00:00"
    }
  },
  "applications": {
    "1": {
      "id": 1,
      "event_id": 1,
      "booth_id": "booth-123",
      "app_ref": "app-test",
      "notes": "Hello",
      "checked": {},
      "status": "submitted",
      "submitted_at": "2026-02-15T19:20:16.581728+00:00",
      "updated_at": "2026-02-15T19:20:16.581755+00:00",
      "vendor_email": null,
      "vendor_id": null
    },
    "2": {
      "id": 2,
      "event_id": 1,
      "booth_id": "string",
      "app_ref": "string",
      "notes": "string",
      "checked": {
        "additionalProp1": true,
        "additionalProp2": true,
        "additionalProp3": true
      },
      "status": "submitted",
      "submitted_at": "2026-02-15T22:25:26.517679+00:00",
      "updated_at": "2026-02-15T22:25:26.517713+00:00",
      "vendor_email": null,
      "vendor_id": null
    },
    "3": {
      "id": 3,
      "event_id": 1,
      "booth_id": "booth-b144a4f591f9-1771092748679",
      "app_ref": "app_29c942e5a6294_1770668231297",
      "notes": "",
      "checked": {
        "c1": true
      },
      "status": "submitted",
      "submitted_at": "2026-02-15T22:27:41.973714+00:00",
      "updated_at": "2026-02-15T22:27:41.973762+00:00",
      "vendor_email": null,
      "vendor_id": null
    },
    "4": {
      "id": 4,
      "event_id": 1,
      "booth_id": "",
      "app_ref": "app_29c942e5a6294_1770668231297",
      "notes": "",
      "checked": {
        "c1": true
      },
      "status": "submitted",
      "submitted_at": "2026-02-15T22:28:15.586463+00:00",
      "updated_at": "2026-02-15T22:28:15.586499+00:00",
      "vendor_email": null,
      "vendor_id": null
    },
    "5": {
      "id": 5,
      "event_id": 1,
      "booth_id": "",
      "app_ref": "app_29c942e5a6294_1770668231297",
      "notes": "",
      "checked": {
        "c1": true
      },
      "status": "submitted",
      "submitted_at": "2026-02-15T22:28:57.256167+00:00",
      "updated_at": "2026-02-15T22:28:57.256196+00:00",
      "vendor_email": null,
      "vendor_id": null
    },
    "6": {
      "id": 6,
      "event_id": 1,
      "booth_id": "",
      "app_ref": "app_29c942e5a6294_1770668231297",
      "notes": "",
      "checked": {
        "c1": true
      },
      "status": "submitted",
      "submitted_at": "2026-02-15T22:44:32.803675+00:00",
      "updated_at": "2026-02-15T22:44:32.803707+00:00",
      "vendor_email": null,
      "vendor_id": null
    },
    "7": {
      "id": 7,
      "event_id": 1,
      "booth_id": "",
      "app_ref": "app_29c942e5a6294_1770668231297",
      "notes": "",
      "checked": {
        "c1": true
      },
      "status": "submitted",
      "submitted_at": "2026-02-15T22:45:03.945909+00:00",
      "updated_at": "2026-02-15T22:45:03.945942+00:00",
      "vendor_email": null,
      "vendor_id": null
    },
    "8": {
      "id": 8,
      "event_id": 1,
      "booth_id": "",
      "app_ref": "app_29c942e5a6294_1770668231297",
      "notes": "",
      "checked": {
        "c1": true
      },
      "status": "submitted",
      "submitted_at": "2026-02-15T22:54:10.975837+00:00",
      "updated_at": "2026-02-15T22:54:10.975866+00:00",
      "vendor_email": null,
      "vendor_id": null
    },
    "9": {
      "id": 9,
      "event_id": 1,
      "booth_id": "",
      "app_ref": "app_29c942e5a6294_1770668231297",
      "notes": "",
      "checked": {
        "c1": true
      },
      "status": "submitted",
      "submitted_at": "2026-02-15T22:59:52.940624+00:00",
      "updated_at": "2026-02-15T22:59:52.940651+00:00",
      "vendor_email": null,
      "vendor_id": null
    },
    "10": {
      "id": 10,
      "event_id": 1,
      "booth_id": "",
      "app_ref": "app_29c942e5a6294_1770668231297",
      "notes": "",
      "checked": {
        "c1": true
      },
      "status": "submitted",
      "submitted_at": "2026-02-15T23:00:38.545027+00:00",
      "updated_at": "2026-02-15T23:00:38.545065+00:00",
      "vendor_email": null,
      "vendor_id": null
    },
    "11": {
      "id": 11,
      "event_id": 1,
      "booth_id": "",
      "app_ref": "app_29c942e5a6294_1770668231297",
      "notes": "",
      "checked": {
        "c1": true
      },
      "status": "submitted",
      "submitted_at": "2026-02-15T23:06:58.246625+00:00",
      "updated_at": "2026-02-15T23:06:58.246657+00:00",
      "vendor_email": null,
      "vendor_id": null
    },
    "12": {
      "id": 12,
      "event_id": 1,
      "booth_id": "",
      "app_ref": "app_29c942e5a6294_1770668231297",
      "notes": "",
      "checked": {
        "c1": true
      },
      "status": "submitted",
      "submitted_at": "2026-02-15T23:13:23.524357+00:00",
      "updated_at": "2026-02-15T23:13:23.524383+00:00",
      "vendor_email": null,
      "vendor_id": null
    },
    "13": {
      "id": 13,
      "event_id": 1,
      "booth_id": null,
      "app_ref": "app_29c942e5a6294_1770668231297",
      "notes": "",
      "checked": {
        "c1": true
      },
      "status": "submitted",
      "submitted_at": "2026-02-15T23:21:02.445226+00:00",
      "updated_at": "2026-02-16T02:14:06.148660+00:00",
      "vendor_email": "vendor@example.com",
      "vendor_id": null
    },
    "14": {
      "id": 14,
      "event_id": 1,
      "booth_id": "booth-b144a4f591f9-1771092748679",
      "app_ref": "app_29c942e5a6294_1770668231297",
      "notes": "",
      "checked": {
        "c1": true
      },
      "status": "approved",
      "submitted_at": "2026-02-15T23:23:23.289092+00:00",
      "updated_at": "2026-02-16T00:15:41.676528+00:00",
      "vendor_email": "Vendor@example.com",
      "vendor_id": null
    },
    "15": {
      "id": 15,
      "event_id": 1,
      "booth_id": null,
      "app_ref": "app_29c942e5a6294_1770668231297",
      "notes": "",
      "checked": {
        "c1": true
      },
      "status": "submitted",
      "submitted_at": "2026-02-16T00:24:25.058940+00:00",
      "updated_at": "2026-02-16T00:24:25.060170+00:00",
      "vendor_email": "Vendor@example.com",
      "vendor_id": null
    },
    "16": {
      "id": 16,
      "event_id": 2,
      "booth_id": null,
      "app_ref": "app_aca1e21ae8e758_1770770596055",
      "notes": "",
      "checked": {},
      "status": "submitted",
      "submitted_at": "2026-02-16T01:19:33.664046+00:00",
      "updated_at": "2026-02-16T01:19:33.664079+00:00",
      "vendor_email": "Vendor@example.com",
      "vendor_id": null
    }
  },
  "layout_meta": {
    "1": {
      "diagram": {
        "elements": [],
        "meta": {}
      },
      "version": 0
    }
  },
  "booths": {},
  "templates": {},
  "next": {
    "event_id": 3,
    "booth_id": 1,
    "template_id": 1,
    "application_id": 17
  }
}
